anonymizer_core/__init__.py
anonymizer_core/dictionary.py
anonymizer_core/ner.py
anonymizer_core/patterns.py
anonymizer_core/presidio_config.py
anonymizer_core/presidio_engine.py
anonymizer_core/protected_titles.py
anonymizer_core/setup_models.py
anonymizer_core/text_anonymizer_integration.py
anonymizer_core/tokenizer.py
anonymizer_gui/__init__.py
anonymizer_gui/gui.py
web/README_ALWAYS_REDACT_API.md
web/__init__.py
web/app.py
web/cli.py
web/run.py
web/templates/index.html
simple_anonymizer-0.1.18.dist-info/LICENSE
simple_anonymizer-0.1.18.dist-info/METADATA
simple_anonymizer-0.1.18.dist-info/WHEEL
simple_anonymizer-0.1.18.dist-info/entry_points.txt
simple_anonymizer-0.1.18.dist-info/RECORD
