Metadata-Version: 2.3
Name: simple-anonymizer
Version: 0.1.18
Summary: Privacy-first text anonymization tool with enterprise-grade accuracy for removing PII from documents
License: Apache-2.0
Keywords: privacy,anonymization,pii,nlp,spacy,presidio,data-protection,text-processing,privacy-tools,gdpr,enterprise
Author: Andrea Tirelli
Author-email: atirellimate@gmail.com
Maintainer: Andrea Tirelli
Maintainer-email: atirellimate@gmail.com
Requires-Python: >=3.9,<3.14
Classifier: Development Status :: 4 - Beta
Classifier: Intended Audience :: Developers
Classifier: Intended Audience :: Information Technology
Classifier: Intended Audience :: Legal Industry
Classifier: Intended Audience :: Healthcare Industry
Classifier: Topic :: Text Processing :: Linguistic
Classifier: Topic :: Security
Classifier: Topic :: Office/Business
Classifier: Topic :: Scientific/Engineering :: Information Analysis
Classifier: License :: OSI Approved :: Apache Software License
Classifier: Programming Language :: Python :: 3
Classifier: Programming Language :: Python :: 3.9
Classifier: Programming Language :: Python :: 3.10
Classifier: Programming Language :: Python :: 3.11
Classifier: Programming Language :: Python :: 3.12
Classifier: Programming Language :: Python :: 3.13
Classifier: Operating System :: OS Independent
Classifier: Environment :: Console
Classifier: Environment :: Web Environment
Classifier: Environment :: X11 Applications :: GTK
Classifier: Natural Language :: English
Provides-Extra: all
Provides-Extra: dev
Provides-Extra: ner
Requires-Dist: black (>=23.9.0) ; extra == "dev"
Requires-Dist: certifi (>=2023.0.0)
Requires-Dist: flask (>=3.1.0)
Requires-Dist: mypy (>=1.5.0) ; extra == "dev"
Requires-Dist: nuitka (>=1.8.0) ; extra == "dev"
Requires-Dist: presidio-analyzer (>=2.2.0)
Requires-Dist: presidio-anonymizer (>=2.2.0)
Requires-Dist: pytest (>=7.4.0) ; extra == "dev"
Requires-Dist: regex (>=2023.0.0)
Requires-Dist: requests (>=2.31.0)
Requires-Dist: ruff (>=0.1.0) ; extra == "dev"
Requires-Dist: spacy (>=3.7.0)
Requires-Dist: spacy (>=3.7.0) ; extra == "all"
Requires-Dist: spacy (>=3.8.0) ; extra == "ner"
Requires-Dist: text-anonymizer (>=0.1.0)
Requires-Dist: unidecode (>=1.3.0)
Requires-Dist: urllib3 (>=2.0.0)
